py_lets_be_rational/__init__.py
py_lets_be_rational/constants.py
py_lets_be_rational/erf_cody.py
py_lets_be_rational/exceptions.py
py_lets_be_rational/lets_be_rational.py
py_lets_be_rational/normaldistribution.py
py_lets_be_rational/numba_helper.py
py_lets_be_rational/rationalcubic.py
py_lets_be_rational_gen-1.0.0.dist-info/METADATA
py_lets_be_rational_gen-1.0.0.dist-info/WHEEL
py_lets_be_rational_gen-1.0.0.dist-info/top_level.txt
py_lets_be_rational_gen-1.0.0.dist-info/RECORD
